Metadata-Version: 1.0
Name: basic-distributions
Version: 0.1
Summary: Gaussian and Binomial distributions
Home-page: UNKNOWN
Author: Matic Princic
Author-email: matic.princic@gmail.com
License: UNKNOWN
Platform: UNKNOWN
